imia/__init__.py
imia/authentication.py
imia/exceptions.py
imia/ext/__init__.py
imia/ext/sqlalchemy.py
imia/impersonation.py
imia/login.py
imia/protocols.py
imia/user_providers.py
imia/user_token.py
imia-0.5.3.dist-info/LICENSE
imia-0.5.3.dist-info/WHEEL
imia-0.5.3.dist-info/METADATA
imia-0.5.3.dist-info/RECORD
