Metadata-Version: 2.1
Name: imia
Version: 0.5.3
Summary: Full stack authentication library for ASGI.
Home-page: https://github.com/alex-oleshkevich/imia
License: MIT
Author: Alex Oleshkevich
Author-email: alex.oleshkevich@gmail.com
Requires-Python: >=3.8.0,<4.0.0
Classifier: Development Status :: 5 - Production/Stable
Classifier: Environment :: Web Environment
Classifier: Intended Audience :: Developers
Classifier: License :: OSI Approved :: MIT License
Classifier: Operating System :: OS Independent
Classifier: Programming Language :: Python :: 3
Classifier: Programming Language :: Python :: 3.10
Classifier: Programming Language :: Python :: 3.8
Classifier: Programming Language :: Python :: 3.9
Classifier: Topic :: Software Development :: Libraries :: Python Modules
Classifier: Typing :: Typed
Provides-Extra: aiosqlite
Provides-Extra: sqlalchemy
Requires-Dist: SQLAlchemy (>=1.4.25,<2.0.0); extra == "sqlalchemy"
Requires-Dist: aiosqlite (>=0.17.0,<0.18.0); extra == "aiosqlite"
Project-URL: Documentation, https://github.com/alex-oleshkevich/imia
Project-URL: Repository, https://github.com/alex-oleshkevich/imia
